ntlib/__init__.py
ntlib/ntl.py
ntlib/NTLArchive/NTLBezoutEquation.py
ntlib/NTLArchive/NTLBinaryEquation.py
ntlib/NTLArchive/NTLCarmichealTest.py
ntlib/NTLArchive/NTLChineseRemainderTheorem.py
ntlib/NTLArchive/NTLCongruence.py
ntlib/NTLArchive/NTLCongruenceSimplification.py
ntlib/NTLArchive/NTLContinuedFraction.py
ntlib/NTLArchive/NTLCoprimalityTest.py
ntlib/NTLArchive/NTLEratosthenesSieve.py
ntlib/NTLArchive/NTLEuclideanAlgorithm.py
ntlib/NTLArchive/NTLEuclideanDivision.py
ntlib/NTLArchive/NTLEulerFunction.py
ntlib/NTLArchive/NTLExceptions.py
ntlib/NTLArchive/NTLFraction.py
ntlib/NTLArchive/NTLGreatestCommonDivisor.py
ntlib/NTLArchive/NTLIndex.py
ntlib/NTLArchive/NTLJacobi.py
ntlib/NTLArchive/NTLJacobiSymbol.py
ntlib/NTLArchive/NTLLeastCommonMultiple.py
ntlib/NTLArchive/NTLLegendre.py
ntlib/NTLArchive/NTLLegendreSymbol.py
ntlib/NTLArchive/NTLOrder.py
ntlib/NTLArchive/NTLPolynomial.py
ntlib/NTLArchive/NTLPolynomialCongruence.py
ntlib/NTLArchive/NTLPolynomialEuclideanDivision.py
ntlib/NTLArchive/NTLPrimeFactorisation.py
ntlib/NTLArchive/NTLPrimitiveResidueClass.py
ntlib/NTLArchive/NTLPrimitiveRoot.py
ntlib/NTLArchive/NTLPseudoPrime.py
ntlib/NTLArchive/NTLQuadratic.py
ntlib/NTLArchive/NTLQuadraticEquation.py
ntlib/NTLArchive/NTLQuadraticFactorisation.py
ntlib/NTLArchive/NTLRepetiveSquareModulo.py
ntlib/NTLArchive/NTLTrivialDivision.py
ntlib/NTLArchive/NTLUtilities.py
ntlib/NTLArchive/NTLValidations.py
ntlib/NTLArchive/__init__.py
ntlib/NTLArchive/__abc__/__init__.py
ntlib/NTLArchive/__abc__/__polynomial__.py
ntlib/NTLArchive/__abc__/__symbol__.py
pyntlib-1.5.0.post4.dist-info/LICENSE
pyntlib-1.5.0.post4.dist-info/METADATA
pyntlib-1.5.0.post4.dist-info/WHEEL
pyntlib-1.5.0.post4.dist-info/top_level.txt
pyntlib-1.5.0.post4.dist-info/RECORD
